[
  {
    "id": 1,
    "name": { "en": "Mary Stuart", "zh": "玛丽·斯图亚特" },
    "requirements": { "emerald": 4, "sapphire": 0, "ruby": 4, "diamond": 0, "onyx": 0 }
  },
  {
    "id": 2,
    "name": { "en": "Niccolò Machiavelli", "zh": "尼科洛·马基雅维利" },
    "requirements": { "emerald": 0, "sapphire": 4, "ruby": 0, "diamond": 4, "onyx": 0 }
  },
  {
    "id": 3,
    "name": { "en": "Isabella I of Castile", "zh": "伊莎贝拉一世" },
    "requirements": { "emerald": 0, "sapphire": 0, "ruby": 0, "diamond": 4, "onyx": 4 }
  },
  {
    "id": 4,
    "name": { "en": "Suleiman the Magnificent", "zh": "苏莱曼大帝" },
    "requirements": { "emerald": 4, "sapphire": 4, "ruby": 0, "diamond": 0, "onyx": 0 }
  },
  {
    "id": 5,
    "name": { "en": "Henry VIII", "zh": "亨利八世" },
    "requirements": { "emerald": 4, "sapphire": 0, "ruby": 0, "diamond": 0, "onyx": 4 }
  },
  {
    "id": 6,
    "name": { "en": "Charles V", "zh": "查理五世" },
    "requirements": { "emerald": 0, "sapphire": 0, "ruby": 3, "diamond": 3, "onyx": 3 }
  },
  {
    "id": 7,
    "name": { "en": "Catherine de' Medici", "zh": "凯瑟琳·德·美第奇" },
    "requirements": { "emerald": 3, "sapphire": 3, "ruby": 3, "diamond": 0, "onyx": 0 }
  },
  {
    "id": 8,
    "name": { "en": "Anne of Brittany", "zh": "布列塔尼的安妮" },
    "requirements": { "emerald": 3, "sapphire": 3, "ruby": 0, "diamond": 3, "onyx": 0 }
  },
  {
    "id": 9,
    "name": { "en": "Elisabeth of Austria", "zh": "奥地利的伊丽莎白" },
    "requirements": { "emerald": 0, "sapphire": 3, "ruby": 0, "diamond": 3, "onyx": 3 }
  },
  {
    "id": 10,
    "name": { "en": "Francis I", "zh": "弗朗索瓦一世" },
    "requirements": { "emerald": 3, "sapphire": 0, "ruby": 3, "diamond": 0, "onyx": 3 }
  }
]
